RCC/__init__.py
RCC/api/abc.py
RCC/api/api.py
RCC/exceptions.py
RCC/http_client.py
RCC/methods.py
RCC/types/base.py
RCC/types/rcc_player.py
RCC/types/response.py
rcc_api-0.1.0.dist-info/WHEEL
rcc_api-0.1.0.dist-info/METADATA
rcc_api-0.1.0.dist-info/RECORD
