Metadata-Version: 2.1
Name: rcc-api
Version: 0.1.0
Summary: Обертка для работа с апи RCC
Home-page: https://github.com/MaHryCT3/RCC_api
License: MIT
Keywords: rust,python,aiohttp,rcc,rustcheatcheck,api
Author: MaHryCT3
Author-email: mahryct123@gmail.com
Requires-Python: >=3.10,<4.0
Classifier: License :: OSI Approved :: MIT License
Classifier: Programming Language :: Python :: 3
Classifier: Programming Language :: Python :: 3.10
Requires-Dist: aiohttp (>=3.8.1,<4.0.0)
Requires-Dist: pydantic (>=1.9.2,<2.0.0)
Project-URL: Repository, https://github.com/MaHryCT3/RCC_api
